coach_claude/__init__.py
coach_claude/claude_settings.py
coach_claude/config.py
coach_claude/daemon.py
coach_claude/database.py
coach_claude/models.py
coach_claude/server.py
coach_claude/skill.py
coach_claude-1.1.0.dist-info/METADATA
coach_claude-1.1.0.dist-info/WHEEL
coach_claude-1.1.0.dist-info/entry_points.txt
coach_claude-1.1.0.dist-info/top_level.txt
coach_claude-1.1.0.dist-info/RECORD
