Metadata-Version: 2.4
Name: coach-claude
Version: 1.1.0
Summary: MCP server for Coach Claude - health and wellness tracking for developers
Author-email: Clutch Engineering <hello@clutch.engineering>
License: Apache-2.0
Project-URL: Homepage, https://github.com/ClutchEngineering/coach-claude
Project-URL: Documentation, https://github.com/ClutchEngineering/coach-claude#readme
Project-URL: Repository, https://github.com/ClutchEngineering/coach-claude
Project-URL: Issues, https://github.com/ClutchEngineering/coach-claude/issues
Keywords: mcp,health,wellness,claude,claude-code,developer-tools
Classifier: Development Status :: 4 - Beta
Classifier: Intended Audience :: Developers
Classifier: License :: OSI Approved :: Apache Software License
Classifier: Programming Language :: Python :: 3
Classifier: Programming Language :: Python :: 3.11
Classifier: Programming Language :: Python :: 3.12
Classifier: Environment :: Console
Classifier: Topic :: Software Development :: Libraries :: Python Modules
Requires-Python: >=3.11
Requires-Dist: mcp>=1.0.0
Requires-Dist: aiosqlite>=0.19.0
Requires-Dist: pydantic>=2.0.0
Requires-Dist: starlette>=0.27.0
Requires-Dist: uvicorn>=0.23.0
Requires-Dist: websockets>=11.0.0
Requires-Dist: sse-starlette>=1.6.0
Provides-Extra: dev
Requires-Dist: pytest>=7.0.0; extra == "dev"
Requires-Dist: pytest-asyncio>=0.21.0; extra == "dev"
Requires-Dist: black>=23.0.0; extra == "dev"
Requires-Dist: ruff>=0.1.0; extra == "dev"
